<?xml version="1.0" ?>
<annotation>
    <folder>BrickRay</folder>
    <filename>03dc071e-db1b-11eb-bc7a-3497f683a169.jpg</filename>
    <size>
        <width>600</width>
        <height>600</height>
        <depth>3</depth>
    </size>
    <object>
        <name>32009</name>
        <difficult>0</difficult>
        <bndbox>
            <xmin>0</xmin>
            <ymin>142</ymin>
            <xmax>297</xmax>
            <ymax>254</ymax>
        </bndbox>
    </object>
    <object>
        <name>15254</name>
        <difficult>0</difficult>
        <bndbox>
            <xmin>470</xmin>
            <ymin>64</ymin>
            <xmax>600</xmax>
            <ymax>246</ymax>
        </bndbox>
    </object>
    <object>
        <name>24309</name>
        <difficult>0</difficult>
        <bndbox>
            <xmin>408</xmin>
            <ymin>293</ymin>
            <xmax>536</xmax>
            <ymax>397</ymax>
        </bndbox>
    </object>
    <object>
        <name>30602</name>
        <difficult>0</difficult>
        <bndbox>
            <xmin>276</xmin>
            <ymin>418</ymin>
            <xmax>379</xmax>
            <ymax>517</ymax>
        </bndbox>
    </object>
</annotation>
