<?xml version="1.0" ?>
<annotation>
    <folder>BrickRay</folder>
    <filename>1145d94a-e3ae-11eb-842e-b0c090bd3910.jpg</filename>
    <size>
        <width>600</width>
        <height>600</height>
        <depth>3</depth>
    </size>
    <object>
        <name>32184</name>
        <difficult>0</difficult>
        <bndbox>
            <xmin>461</xmin>
            <ymin>511</ymin>
            <xmax>527</xmax>
            <ymax>563</ymax>
        </bndbox>
    </object>
    <object>
        <name>2465</name>
        <difficult>0</difficult>
        <bndbox>
            <xmin>222</xmin>
            <ymin>0</ymin>
            <xmax>520</xmax>
            <ymax>440</ymax>
        </bndbox>
    </object>
    <object>
        <name>99781</name>
        <difficult>0</difficult>
        <bndbox>
            <xmin>267</xmin>
            <ymin>240</ymin>
            <xmax>336</xmax>
            <ymax>321</ymax>
        </bndbox>
    </object>
    <object>
        <name>3684c</name>
        <difficult>0</difficult>
        <bndbox>
            <xmin>74</xmin>
            <ymin>497</ymin>
            <xmax>170</xmax>
            <ymax>600</ymax>
        </bndbox>
    </object>
</annotation>
