<?xml version="1.0" ?>
<annotation>
    <folder>BrickRay</folder>
    <filename>11951ab4-da79-11eb-b0a3-3497f683a169.jpg</filename>
    <size>
        <width>600</width>
        <height>600</height>
        <depth>3</depth>
    </size>
    <object>
        <name>30562</name>
        <difficult>0</difficult>
        <bndbox>
            <xmin>0</xmin>
            <ymin>149</ymin>
            <xmax>178</xmax>
            <ymax>292</ymax>
        </bndbox>
    </object>
    <object>
        <name>14718</name>
        <difficult>0</difficult>
        <bndbox>
            <xmin>499</xmin>
            <ymin>200</ymin>
            <xmax>600</xmax>
            <ymax>304</ymax>
        </bndbox>
    </object>
    <object>
        <name>30176</name>
        <difficult>0</difficult>
        <bndbox>
            <xmin>332</xmin>
            <ymin>381</ymin>
            <xmax>408</xmax>
            <ymax>457</ymax>
        </bndbox>
    </object>
    <object>
        <name>60608</name>
        <difficult>0</difficult>
        <bndbox>
            <xmin>262</xmin>
            <ymin>252</ymin>
            <xmax>300</xmax>
            <ymax>314</ymax>
        </bndbox>
    </object>
</annotation>
