<?xml version="1.0" ?>
<annotation>
    <folder>BrickRay</folder>
    <filename>157245ae-e4a7-11eb-85ef-b0c090bd3910.jpg</filename>
    <size>
        <width>600</width>
        <height>600</height>
        <depth>3</depth>
    </size>
    <object>
        <name>60470</name>
        <difficult>0</difficult>
        <bndbox>
            <xmin>353</xmin>
            <ymin>453</ymin>
            <xmax>509</xmax>
            <ymax>600</ymax>
        </bndbox>
    </object>
    <object>
        <name>41677</name>
        <difficult>0</difficult>
        <bndbox>
            <xmin>456</xmin>
            <ymin>389</ymin>
            <xmax>539</xmax>
            <ymax>518</ymax>
        </bndbox>
    </object>
    <object>
        <name>60485</name>
        <difficult>0</difficult>
        <bndbox>
            <xmin>3</xmin>
            <ymin>0</ymin>
            <xmax>412</xmax>
            <ymax>59</ymax>
        </bndbox>
    </object>
    <object>
        <name>30552</name>
        <difficult>0</difficult>
        <bndbox>
            <xmin>532</xmin>
            <ymin>67</ymin>
            <xmax>596</xmax>
            <ymax>155</ymax>
        </bndbox>
    </object>
</annotation>
