<?xml version="1.0" ?>
<annotation>
    <folder>BrickRay</folder>
    <filename>19495912-e4c3-11eb-b0c4-b0c090bd3910.jpg</filename>
    <size>
        <width>600</width>
        <height>600</height>
        <depth>3</depth>
    </size>
    <object>
        <name>11946</name>
        <difficult>0</difficult>
        <bndbox>
            <xmin>207</xmin>
            <ymin>501</ymin>
            <xmax>464</xmax>
            <ymax>600</ymax>
        </bndbox>
    </object>
    <object>
        <name>41678</name>
        <difficult>0</difficult>
        <bndbox>
            <xmin>118</xmin>
            <ymin>308</ymin>
            <xmax>230</xmax>
            <ymax>422</ymax>
        </bndbox>
    </object>
    <object>
        <name>18041</name>
        <difficult>0</difficult>
        <bndbox>
            <xmin>3</xmin>
            <ymin>426</ymin>
            <xmax>64</xmax>
            <ymax>475</ymax>
        </bndbox>
    </object>
    <object>
        <name>3024</name>
        <difficult>0</difficult>
        <bndbox>
            <xmin>549</xmin>
            <ymin>0</ymin>
            <xmax>597</xmax>
            <ymax>48</ymax>
        </bndbox>
    </object>
</annotation>
