<?xml version="1.0" ?>
<annotation>
    <folder>BrickRay</folder>
    <filename>198ac6a6-db32-11eb-958f-3497f683a169.jpg</filename>
    <size>
        <width>600</width>
        <height>600</height>
        <depth>3</depth>
    </size>
    <object>
        <name>58176</name>
        <difficult>0</difficult>
        <bndbox>
            <xmin>0</xmin>
            <ymin>209</ymin>
            <xmax>35</xmax>
            <ymax>247</ymax>
        </bndbox>
    </object>
    <object>
        <name>43723</name>
        <difficult>0</difficult>
        <bndbox>
            <xmin>521</xmin>
            <ymin>298</ymin>
            <xmax>599</xmax>
            <ymax>418</ymax>
        </bndbox>
    </object>
    <object>
        <name>3839b</name>
        <difficult>0</difficult>
        <bndbox>
            <xmin>444</xmin>
            <ymin>104</ymin>
            <xmax>559</xmax>
            <ymax>179</ymax>
        </bndbox>
    </object>
    <object>
        <name>2456</name>
        <difficult>0</difficult>
        <bndbox>
            <xmin>94</xmin>
            <ymin>367</ymin>
            <xmax>348</xmax>
            <ymax>476</ymax>
        </bndbox>
    </object>
</annotation>
