<?xml version="1.0" ?>
<annotation>
    <folder>BrickRay</folder>
    <filename>1ed0b44a-e5cb-11eb-9b65-b0c090bd3910.jpg</filename>
    <size>
        <width>300</width>
        <height>300</height>
        <depth>3</depth>
    </size>
    <object>
        <name>32009</name>
        <difficult>0</difficult>
        <bndbox>
            <xmin>9</xmin>
            <ymin>0</ymin>
            <xmax>292</xmax>
            <ymax>300</ymax>
        </bndbox>
    </object>
    <object>
        <name>2412b</name>
        <difficult>0</difficult>
        <bndbox>
            <xmin>194</xmin>
            <ymin>107</ymin>
            <xmax>263</xmax>
            <ymax>190</ymax>
        </bndbox>
    </object>
</annotation>
