<?xml version="1.0" ?>
<annotation>
    <folder>BrickRay</folder>
    <filename>21250f88-d9d3-11eb-a9f9-3497f683a169.jpg</filename>
    <size>
        <width>600</width>
        <height>600</height>
        <depth>3</depth>
    </size>
    <object>
        <name>30663</name>
        <difficult>0</difficult>
        <bndbox>
            <xmin>333</xmin>
            <ymin>132</ymin>
            <xmax>385</xmax>
            <ymax>172</ymax>
        </bndbox>
    </object>
    <object>
        <name>64782</name>
        <difficult>0</difficult>
        <bndbox>
            <xmin>107</xmin>
            <ymin>285</ymin>
            <xmax>497</xmax>
            <ymax>600</ymax>
        </bndbox>
    </object>
    <object>
        <name>2655</name>
        <difficult>0</difficult>
        <bndbox>
            <xmin>367</xmin>
            <ymin>130</ymin>
            <xmax>421</xmax>
            <ymax>179</ymax>
        </bndbox>
    </object>
    <object>
        <name>4346</name>
        <difficult>0</difficult>
        <bndbox>
            <xmin>329</xmin>
            <ymin>0</ymin>
            <xmax>378</xmax>
            <ymax>69</ymax>
        </bndbox>
    </object>
</annotation>
