<?xml version="1.0" ?>
<annotation>
    <folder>BrickRay</folder>
    <filename>23a55e62-db56-11eb-aaf5-3497f683a169.jpg</filename>
    <size>
        <width>600</width>
        <height>600</height>
        <depth>3</depth>
    </size>
    <object>
        <name>23443</name>
        <difficult>0</difficult>
        <bndbox>
            <xmin>558</xmin>
            <ymin>140</ymin>
            <xmax>600</xmax>
            <ymax>203</ymax>
        </bndbox>
    </object>
    <object>
        <name>15571</name>
        <difficult>0</difficult>
        <bndbox>
            <xmin>455</xmin>
            <ymin>311</ymin>
            <xmax>540</xmax>
            <ymax>364</ymax>
        </bndbox>
    </object>
    <object>
        <name>3069b</name>
        <difficult>0</difficult>
        <bndbox>
            <xmin>178</xmin>
            <ymin>362</ymin>
            <xmax>271</xmax>
            <ymax>420</ymax>
        </bndbox>
    </object>
    <object>
        <name>3623</name>
        <difficult>0</difficult>
        <bndbox>
            <xmin>0</xmin>
            <ymin>374</ymin>
            <xmax>139</xmax>
            <ymax>442</ymax>
        </bndbox>
    </object>
</annotation>
