<?xml version="1.0" ?>
<annotation>
    <folder>BrickRay</folder>
    <filename>23b9d4cc-da09-11eb-ba56-3497f683a169.jpg</filename>
    <size>
        <width>600</width>
        <height>600</height>
        <depth>3</depth>
    </size>
    <object>
        <name>32474</name>
        <difficult>0</difficult>
        <bndbox>
            <xmin>497</xmin>
            <ymin>535</ymin>
            <xmax>560</xmax>
            <ymax>600</ymax>
        </bndbox>
    </object>
    <object>
        <name>55982</name>
        <difficult>0</difficult>
        <bndbox>
            <xmin>265</xmin>
            <ymin>0</ymin>
            <xmax>335</xmax>
            <ymax>69</ymax>
        </bndbox>
    </object>
    <object>
        <name>20310</name>
        <difficult>0</difficult>
        <bndbox>
            <xmin>20</xmin>
            <ymin>120</ymin>
            <xmax>91</xmax>
            <ymax>185</ymax>
        </bndbox>
    </object>
    <object>
        <name>54383</name>
        <difficult>0</difficult>
        <bndbox>
            <xmin>395</xmin>
            <ymin>271</ymin>
            <xmax>576</xmax>
            <ymax>468</ymax>
        </bndbox>
    </object>
</annotation>
