<?xml version="1.0" ?>
<annotation>
    <folder>BrickRay</folder>
    <filename>28d84f4c-d9c5-11eb-ac73-3497f683a169.jpg</filename>
    <size>
        <width>600</width>
        <height>600</height>
        <depth>3</depth>
    </size>
    <object>
        <name>60849</name>
        <difficult>0</difficult>
        <bndbox>
            <xmin>499</xmin>
            <ymin>324</ymin>
            <xmax>599</xmax>
            <ymax>370</ymax>
        </bndbox>
    </object>
    <object>
        <name>6636</name>
        <difficult>0</difficult>
        <bndbox>
            <xmin>0</xmin>
            <ymin>301</ymin>
            <xmax>103</xmax>
            <ymax>560</ymax>
        </bndbox>
    </object>
    <object>
        <name>44567</name>
        <difficult>0</difficult>
        <bndbox>
            <xmin>284</xmin>
            <ymin>21</ymin>
            <xmax>340</xmax>
            <ymax>68</ymax>
        </bndbox>
    </object>
    <object>
        <name>43093</name>
        <difficult>0</difficult>
        <bndbox>
            <xmin>10</xmin>
            <ymin>122</ymin>
            <xmax>48</xmax>
            <ymax>185</ymax>
        </bndbox>
    </object>
</annotation>
