<?xml version="1.0" ?>
<annotation>
    <folder>BrickRay</folder>
    <filename>2e839162-e67c-11eb-984e-b0c090bd3910.jpg</filename>
    <size>
        <width>300</width>
        <height>300</height>
        <depth>3</depth>
    </size>
    <object>
        <name>15208</name>
        <difficult>0</difficult>
        <bndbox>
            <xmin>233</xmin>
            <ymin>85</ymin>
            <xmax>300</xmax>
            <ymax>166</ymax>
        </bndbox>
    </object>
    <object>
        <name>4287</name>
        <difficult>0</difficult>
        <bndbox>
            <xmin>0</xmin>
            <ymin>145</ymin>
            <xmax>123</xmax>
            <ymax>207</ymax>
        </bndbox>
    </object>
</annotation>
