<?xml version="1.0" ?>
<annotation>
    <folder>BrickRay</folder>
    <filename>355a72b8-e463-11eb-860c-b0c090bd3910.jpg</filename>
    <size>
        <width>600</width>
        <height>600</height>
        <depth>3</depth>
    </size>
    <object>
        <name>32449</name>
        <difficult>0</difficult>
        <bndbox>
            <xmin>191</xmin>
            <ymin>0</ymin>
            <xmax>232</xmax>
            <ymax>138</ymax>
        </bndbox>
    </object>
    <object>
        <name>43719</name>
        <difficult>0</difficult>
        <bndbox>
            <xmin>116</xmin>
            <ymin>353</ymin>
            <xmax>290</xmax>
            <ymax>535</ymax>
        </bndbox>
    </object>
    <object>
        <name>30357</name>
        <difficult>0</difficult>
        <bndbox>
            <xmin>327</xmin>
            <ymin>454</ymin>
            <xmax>471</xmax>
            <ymax>599</ymax>
        </bndbox>
    </object>
    <object>
        <name>95344</name>
        <difficult>0</difficult>
        <bndbox>
            <xmin>112</xmin>
            <ymin>24</ymin>
            <xmax>180</xmax>
            <ymax>61</ymax>
        </bndbox>
    </object>
</annotation>
