<?xml version="1.0" ?>
<annotation>
    <folder>BrickRay</folder>
    <filename>39b3df12-e4e6-11eb-b609-b0c090bd3910.jpg</filename>
    <size>
        <width>600</width>
        <height>600</height>
        <depth>3</depth>
    </size>
    <object>
        <name>32124</name>
        <difficult>0</difficult>
        <bndbox>
            <xmin>0</xmin>
            <ymin>55</ymin>
            <xmax>140</xmax>
            <ymax>195</ymax>
        </bndbox>
    </object>
    <object>
        <name>30663</name>
        <difficult>0</difficult>
        <bndbox>
            <xmin>499</xmin>
            <ymin>425</ymin>
            <xmax>600</xmax>
            <ymax>524</ymax>
        </bndbox>
    </object>
    <object>
        <name>11833</name>
        <difficult>0</difficult>
        <bndbox>
            <xmin>394</xmin>
            <ymin>221</ymin>
            <xmax>571</xmax>
            <ymax>382</ymax>
        </bndbox>
    </object>
    <object>
        <name>30350b</name>
        <difficult>0</difficult>
        <bndbox>
            <xmin>164</xmin>
            <ymin>138</ymin>
            <xmax>330</xmax>
            <ymax>262</ymax>
        </bndbox>
    </object>
</annotation>
