<?xml version="1.0" ?>
<annotation>
    <folder>BrickRay</folder>
    <filename>3c32f47e-d96d-11eb-9865-b0c090bd3910.jpg</filename>
    <size>
        <width>600</width>
        <height>600</height>
        <depth>3</depth>
    </size>
    <object>
        <name>41678</name>
        <difficult>0</difficult>
        <bndbox>
            <xmin>461</xmin>
            <ymin>97</ymin>
            <xmax>528</xmax>
            <ymax>150</ymax>
        </bndbox>
    </object>
    <object>
        <name>53585</name>
        <difficult>0</difficult>
        <bndbox>
            <xmin>0</xmin>
            <ymin>364</ymin>
            <xmax>45</xmax>
            <ymax>407</ymax>
        </bndbox>
    </object>
    <object>
        <name>14720</name>
        <difficult>0</difficult>
        <bndbox>
            <xmin>417</xmin>
            <ymin>308</ymin>
            <xmax>600</xmax>
            <ymax>456</ymax>
        </bndbox>
    </object>
    <object>
        <name>30165</name>
        <difficult>0</difficult>
        <bndbox>
            <xmin>208</xmin>
            <ymin>250</ymin>
            <xmax>291</xmax>
            <ymax>328</ymax>
        </bndbox>
    </object>
</annotation>
