<?xml version="1.0" ?>
<annotation>
    <folder>BrickRay</folder>
    <filename>3c977968-e2da-11eb-9b33-b0c090bd3910.jpg</filename>
    <size>
        <width>600</width>
        <height>600</height>
        <depth>3</depth>
    </size>
    <object>
        <name>50950</name>
        <difficult>0</difficult>
        <bndbox>
            <xmin>82</xmin>
            <ymin>226</ymin>
            <xmax>272</xmax>
            <ymax>352</ymax>
        </bndbox>
    </object>
    <object>
        <name>99207</name>
        <difficult>0</difficult>
        <bndbox>
            <xmin>117</xmin>
            <ymin>106</ymin>
            <xmax>220</xmax>
            <ymax>254</ymax>
        </bndbox>
    </object>
    <object>
        <name>11203</name>
        <difficult>0</difficult>
        <bndbox>
            <xmin>136</xmin>
            <ymin>0</ymin>
            <xmax>247</xmax>
            <ymax>77</ymax>
        </bndbox>
    </object>
    <object>
        <name>6215</name>
        <difficult>0</difficult>
        <bndbox>
            <xmin>328</xmin>
            <ymin>373</ymin>
            <xmax>505</xmax>
            <ymax>599</ymax>
        </bndbox>
    </object>
</annotation>
