<?xml version="1.0" ?>
<annotation>
    <folder>BrickRay</folder>
    <filename>3e884900-d93c-11eb-9488-b0c090bd3910.jpg</filename>
    <size>
        <width>600</width>
        <height>600</height>
        <depth>3</depth>
    </size>
    <object>
        <name>76766</name>
        <difficult>0</difficult>
        <bndbox>
            <xmin>378</xmin>
            <ymin>253</ymin>
            <xmax>506</xmax>
            <ymax>407</ymax>
        </bndbox>
    </object>
    <object>
        <name>58176</name>
        <difficult>0</difficult>
        <bndbox>
            <xmin>102</xmin>
            <ymin>507</ymin>
            <xmax>128</xmax>
            <ymax>532</ymax>
        </bndbox>
    </object>
    <object>
        <name>93606</name>
        <difficult>0</difficult>
        <bndbox>
            <xmin>247</xmin>
            <ymin>0</ymin>
            <xmax>343</xmax>
            <ymax>97</ymax>
        </bndbox>
    </object>
    <object>
        <name>3633</name>
        <difficult>0</difficult>
        <bndbox>
            <xmin>271</xmin>
            <ymin>494</ymin>
            <xmax>377</xmax>
            <ymax>599</ymax>
        </bndbox>
    </object>
</annotation>
