<?xml version="1.0" ?>
<annotation>
    <folder>BrickRay</folder>
    <filename>419a97c0-d966-11eb-9811-b0c090bd3910.jpg</filename>
    <size>
        <width>600</width>
        <height>600</height>
        <depth>3</depth>
    </size>
    <object>
        <name>2339</name>
        <difficult>0</difficult>
        <bndbox>
            <xmin>256</xmin>
            <ymin>0</ymin>
            <xmax>432</xmax>
            <ymax>176</ymax>
        </bndbox>
    </object>
    <object>
        <name>46212</name>
        <difficult>0</difficult>
        <bndbox>
            <xmin>234</xmin>
            <ymin>23</ymin>
            <xmax>306</xmax>
            <ymax>221</ymax>
        </bndbox>
    </object>
    <object>
        <name>30602</name>
        <difficult>0</difficult>
        <bndbox>
            <xmin>223</xmin>
            <ymin>407</ymin>
            <xmax>333</xmax>
            <ymax>514</ymax>
        </bndbox>
    </object>
    <object>
        <name>32009</name>
        <difficult>0</difficult>
        <bndbox>
            <xmin>146</xmin>
            <ymin>299</ymin>
            <xmax>438</xmax>
            <ymax>600</ymax>
        </bndbox>
    </object>
</annotation>
