<?xml version="1.0" ?>
<annotation>
    <folder>BrickRay</folder>
    <filename>52efdcf6-e3ad-11eb-aac1-b0c090bd3910.jpg</filename>
    <size>
        <width>600</width>
        <height>600</height>
        <depth>3</depth>
    </size>
    <object>
        <name>4519</name>
        <difficult>0</difficult>
        <bndbox>
            <xmin>0</xmin>
            <ymin>282</ymin>
            <xmax>79</xmax>
            <ymax>365</ymax>
        </bndbox>
    </object>
    <object>
        <name>41239</name>
        <difficult>0</difficult>
        <bndbox>
            <xmin>235</xmin>
            <ymin>238</ymin>
            <xmax>600</xmax>
            <ymax>489</ymax>
        </bndbox>
    </object>
    <object>
        <name>3065</name>
        <difficult>0</difficult>
        <bndbox>
            <xmin>194</xmin>
            <ymin>94</ymin>
            <xmax>255</xmax>
            <ymax>167</ymax>
        </bndbox>
    </object>
    <object>
        <name>55981</name>
        <difficult>0</difficult>
        <bndbox>
            <xmin>170</xmin>
            <ymin>363</ymin>
            <xmax>260</xmax>
            <ymax>455</ymax>
        </bndbox>
    </object>
</annotation>
