<?xml version="1.0" ?>
<annotation>
    <folder>BrickRay</folder>
    <filename>56ad6f00-da89-11eb-9a5c-3497f683a169.jpg</filename>
    <size>
        <width>600</width>
        <height>600</height>
        <depth>3</depth>
    </size>
    <object>
        <name>3005</name>
        <difficult>0</difficult>
        <bndbox>
            <xmin>497</xmin>
            <ymin>34</ymin>
            <xmax>541</xmax>
            <ymax>91</ymax>
        </bndbox>
    </object>
    <object>
        <name>18646</name>
        <difficult>0</difficult>
        <bndbox>
            <xmin>0</xmin>
            <ymin>379</ymin>
            <xmax>273</xmax>
            <ymax>548</ymax>
        </bndbox>
    </object>
    <object>
        <name>63868</name>
        <difficult>0</difficult>
        <bndbox>
            <xmin>333</xmin>
            <ymin>35</ymin>
            <xmax>424</xmax>
            <ymax>74</ymax>
        </bndbox>
    </object>
    <object>
        <name>24375</name>
        <difficult>0</difficult>
        <bndbox>
            <xmin>566</xmin>
            <ymin>144</ymin>
            <xmax>600</xmax>
            <ymax>176</ymax>
        </bndbox>
    </object>
</annotation>
