<?xml version="1.0" ?>
<annotation>
    <folder>BrickRay</folder>
    <filename>5be3320a-e4ed-11eb-99ad-b0c090bd3910.jpg</filename>
    <size>
        <width>600</width>
        <height>600</height>
        <depth>3</depth>
    </size>
    <object>
        <name>48989</name>
        <difficult>0</difficult>
        <bndbox>
            <xmin>117</xmin>
            <ymin>182</ymin>
            <xmax>258</xmax>
            <ymax>297</ymax>
        </bndbox>
    </object>
    <object>
        <name>30565</name>
        <difficult>0</difficult>
        <bndbox>
            <xmin>311</xmin>
            <ymin>398</ymin>
            <xmax>512</xmax>
            <ymax>600</ymax>
        </bndbox>
    </object>
    <object>
        <name>63965</name>
        <difficult>0</difficult>
        <bndbox>
            <xmin>48</xmin>
            <ymin>0</ymin>
            <xmax>119</xmax>
            <ymax>208</ymax>
        </bndbox>
    </object>
    <object>
        <name>63869</name>
        <difficult>0</difficult>
        <bndbox>
            <xmin>478</xmin>
            <ymin>386</ymin>
            <xmax>547</xmax>
            <ymax>518</ymax>
        </bndbox>
    </object>
</annotation>
