<?xml version="1.0" ?>
<annotation>
    <folder>BrickRay</folder>
    <filename>5c119ede-dab6-11eb-bdcc-3497f683a169.jpg</filename>
    <size>
        <width>600</width>
        <height>600</height>
        <depth>3</depth>
    </size>
    <object>
        <name>34103</name>
        <difficult>0</difficult>
        <bndbox>
            <xmin>503</xmin>
            <ymin>61</ymin>
            <xmax>600</xmax>
            <ymax>100</ymax>
        </bndbox>
    </object>
    <object>
        <name>41740</name>
        <difficult>0</difficult>
        <bndbox>
            <xmin>355</xmin>
            <ymin>4</ymin>
            <xmax>478</xmax>
            <ymax>44</ymax>
        </bndbox>
    </object>
    <object>
        <name>11478</name>
        <difficult>0</difficult>
        <bndbox>
            <xmin>0</xmin>
            <ymin>262</ymin>
            <xmax>58</xmax>
            <ymax>429</ymax>
        </bndbox>
    </object>
    <object>
        <name>47397</name>
        <difficult>0</difficult>
        <bndbox>
            <xmin>84</xmin>
            <ymin>181</ymin>
            <xmax>236</xmax>
            <ymax>594</ymax>
        </bndbox>
    </object>
</annotation>
