<?xml version="1.0" ?>
<annotation>
    <folder>BrickRay</folder>
    <filename>655b2480-d96f-11eb-b901-b0c090bd3910.jpg</filename>
    <size>
        <width>600</width>
        <height>600</height>
        <depth>3</depth>
    </size>
    <object>
        <name>3710</name>
        <difficult>0</difficult>
        <bndbox>
            <xmin>88</xmin>
            <ymin>324</ymin>
            <xmax>161</xmax>
            <ymax>401</ymax>
        </bndbox>
    </object>
    <object>
        <name>4185</name>
        <difficult>0</difficult>
        <bndbox>
            <xmin>543</xmin>
            <ymin>157</ymin>
            <xmax>600</xmax>
            <ymax>212</ymax>
        </bndbox>
    </object>
    <object>
        <name>3960</name>
        <difficult>0</difficult>
        <bndbox>
            <xmin>98</xmin>
            <ymin>345</ymin>
            <xmax>189</xmax>
            <ymax>432</ymax>
        </bndbox>
    </object>
    <object>
        <name>57909</name>
        <difficult>0</difficult>
        <bndbox>
            <xmin>0</xmin>
            <ymin>145</ymin>
            <xmax>67</xmax>
            <ymax>211</ymax>
        </bndbox>
    </object>
</annotation>
