<?xml version="1.0" ?>
<annotation>
    <folder>BrickRay</folder>
    <filename>68d6c35a-e2ed-11eb-a601-b0c090bd3910.jpg</filename>
    <size>
        <width>600</width>
        <height>600</height>
        <depth>3</depth>
    </size>
    <object>
        <name>11477</name>
        <difficult>0</difficult>
        <bndbox>
            <xmin>0</xmin>
            <ymin>135</ymin>
            <xmax>68</xmax>
            <ymax>174</ymax>
        </bndbox>
    </object>
    <object>
        <name>48729</name>
        <difficult>0</difficult>
        <bndbox>
            <xmin>566</xmin>
            <ymin>111</ymin>
            <xmax>600</xmax>
            <ymax>171</ymax>
        </bndbox>
    </object>
    <object>
        <name>3068b</name>
        <difficult>0</difficult>
        <bndbox>
            <xmin>28</xmin>
            <ymin>388</ymin>
            <xmax>161</xmax>
            <ymax>507</ymax>
        </bndbox>
    </object>
    <object>
        <name>32009</name>
        <difficult>0</difficult>
        <bndbox>
            <xmin>113</xmin>
            <ymin>59</ymin>
            <xmax>304</xmax>
            <ymax>284</ymax>
        </bndbox>
    </object>
</annotation>
