<?xml version="1.0" ?>
<annotation>
    <folder>BrickRay</folder>
    <filename>6b645ae6-e5c2-11eb-94b5-b0c090bd3910.jpg</filename>
    <size>
        <width>300</width>
        <height>300</height>
        <depth>3</depth>
    </size>
    <object>
        <name>52107</name>
        <difficult>0</difficult>
        <bndbox>
            <xmin>127</xmin>
            <ymin>0</ymin>
            <xmax>186</xmax>
            <ymax>86</ymax>
        </bndbox>
    </object>
    <object>
        <name>30162</name>
        <difficult>0</difficult>
        <bndbox>
            <xmin>107</xmin>
            <ymin>230</ymin>
            <xmax>194</xmax>
            <ymax>300</ymax>
        </bndbox>
    </object>
</annotation>
