<?xml version="1.0" ?>
<annotation>
    <folder>BrickRay</folder>
    <filename>6dd8e274-da01-11eb-9a9f-3497f683a169.jpg</filename>
    <size>
        <width>600</width>
        <height>600</height>
        <depth>3</depth>
    </size>
    <object>
        <name>60476</name>
        <difficult>0</difficult>
        <bndbox>
            <xmin>293</xmin>
            <ymin>421</ymin>
            <xmax>375</xmax>
            <ymax>516</ymax>
        </bndbox>
    </object>
    <object>
        <name>98100</name>
        <difficult>0</difficult>
        <bndbox>
            <xmin>349</xmin>
            <ymin>0</ymin>
            <xmax>432</xmax>
            <ymax>88</ymax>
        </bndbox>
    </object>
    <object>
        <name>36840</name>
        <difficult>0</difficult>
        <bndbox>
            <xmin>205</xmin>
            <ymin>85</ymin>
            <xmax>273</xmax>
            <ymax>166</ymax>
        </bndbox>
    </object>
    <object>
        <name>42003</name>
        <difficult>0</difficult>
        <bndbox>
            <xmin>237</xmin>
            <ymin>518</ymin>
            <xmax>315</xmax>
            <ymax>600</ymax>
        </bndbox>
    </object>
</annotation>
