<?xml version="1.0" ?>
<annotation>
    <folder>BrickRay</folder>
    <filename>6fa41e12-e46f-11eb-b024-b0c090bd3910.jpg</filename>
    <size>
        <width>600</width>
        <height>600</height>
        <depth>3</depth>
    </size>
    <object>
        <name>39739</name>
        <difficult>0</difficult>
        <bndbox>
            <xmin>386</xmin>
            <ymin>49</ymin>
            <xmax>461</xmax>
            <ymax>103</ymax>
        </bndbox>
    </object>
    <object>
        <name>41677</name>
        <difficult>0</difficult>
        <bndbox>
            <xmin>489</xmin>
            <ymin>71</ymin>
            <xmax>589</xmax>
            <ymax>144</ymax>
        </bndbox>
    </object>
    <object>
        <name>40344</name>
        <difficult>0</difficult>
        <bndbox>
            <xmin>0</xmin>
            <ymin>64</ymin>
            <xmax>504</xmax>
            <ymax>502</ymax>
        </bndbox>
    </object>
    <object>
        <name>4477</name>
        <difficult>0</difficult>
        <bndbox>
            <xmin>117</xmin>
            <ymin>64</ymin>
            <xmax>600</xmax>
            <ymax>515</ymax>
        </bndbox>
    </object>
</annotation>
