<?xml version="1.0" ?>
<annotation>
    <folder>BrickRay</folder>
    <filename>7c5498e4-db44-11eb-894c-3497f683a169.jpg</filename>
    <size>
        <width>600</width>
        <height>600</height>
        <depth>3</depth>
    </size>
    <object>
        <name>3679</name>
        <difficult>0</difficult>
        <bndbox>
            <xmin>91</xmin>
            <ymin>72</ymin>
            <xmax>162</xmax>
            <ymax>124</ymax>
        </bndbox>
    </object>
    <object>
        <name>32556</name>
        <difficult>0</difficult>
        <bndbox>
            <xmin>327</xmin>
            <ymin>282</ymin>
            <xmax>484</xmax>
            <ymax>323</ymax>
        </bndbox>
    </object>
    <object>
        <name>88930</name>
        <difficult>0</difficult>
        <bndbox>
            <xmin>351</xmin>
            <ymin>354</ymin>
            <xmax>600</xmax>
            <ymax>487</ymax>
        </bndbox>
    </object>
    <object>
        <name>60478</name>
        <difficult>0</difficult>
        <bndbox>
            <xmin>0</xmin>
            <ymin>166</ymin>
            <xmax>132</xmax>
            <ymax>220</ymax>
        </bndbox>
    </object>
</annotation>
