<?xml version="1.0" ?>
<annotation>
    <folder>BrickRay</folder>
    <filename>7e224d92-da9c-11eb-bae9-3497f683a169.jpg</filename>
    <size>
        <width>600</width>
        <height>600</height>
        <depth>3</depth>
    </size>
    <object>
        <name>98282</name>
        <difficult>0</difficult>
        <bndbox>
            <xmin>60</xmin>
            <ymin>361</ymin>
            <xmax>202</xmax>
            <ymax>509</ymax>
        </bndbox>
    </object>
    <object>
        <name>30562</name>
        <difficult>0</difficult>
        <bndbox>
            <xmin>224</xmin>
            <ymin>0</ymin>
            <xmax>332</xmax>
            <ymax>326</ymax>
        </bndbox>
    </object>
    <object>
        <name>85080</name>
        <difficult>0</difficult>
        <bndbox>
            <xmin>183</xmin>
            <ymin>255</ymin>
            <xmax>239</xmax>
            <ymax>353</ymax>
        </bndbox>
    </object>
    <object>
        <name>3960</name>
        <difficult>0</difficult>
        <bndbox>
            <xmin>368</xmin>
            <ymin>437</ymin>
            <xmax>536</xmax>
            <ymax>600</ymax>
        </bndbox>
    </object>
</annotation>
