<?xml version="1.0" ?>
<annotation>
    <folder>BrickRay</folder>
    <filename>8abc3282-da39-11eb-b192-3497f683a169.jpg</filename>
    <size>
        <width>600</width>
        <height>600</height>
        <depth>3</depth>
    </size>
    <object>
        <name>3069b</name>
        <difficult>0</difficult>
        <bndbox>
            <xmin>293</xmin>
            <ymin>290</ymin>
            <xmax>352</xmax>
            <ymax>321</ymax>
        </bndbox>
    </object>
    <object>
        <name>3005</name>
        <difficult>0</difficult>
        <bndbox>
            <xmin>246</xmin>
            <ymin>564</ymin>
            <xmax>280</xmax>
            <ymax>600</ymax>
        </bndbox>
    </object>
    <object>
        <name>6558</name>
        <difficult>0</difficult>
        <bndbox>
            <xmin>258</xmin>
            <ymin>400</ymin>
            <xmax>349</xmax>
            <ymax>424</ymax>
        </bndbox>
    </object>
    <object>
        <name>4185</name>
        <difficult>0</difficult>
        <bndbox>
            <xmin>321</xmin>
            <ymin>0</ymin>
            <xmax>401</xmax>
            <ymax>60</ymax>
        </bndbox>
    </object>
</annotation>
