<?xml version="1.0" ?>
<annotation>
    <folder>BrickRay</folder>
    <filename>95323d18-e3bb-11eb-9726-b0c090bd3910.jpg</filename>
    <size>
        <width>600</width>
        <height>600</height>
        <depth>3</depth>
    </size>
    <object>
        <name>18671</name>
        <difficult>0</difficult>
        <bndbox>
            <xmin>143</xmin>
            <ymin>40</ymin>
            <xmax>294</xmax>
            <ymax>148</ymax>
        </bndbox>
    </object>
    <object>
        <name>32009</name>
        <difficult>0</difficult>
        <bndbox>
            <xmin>211</xmin>
            <ymin>83</ymin>
            <xmax>600</xmax>
            <ymax>349</ymax>
        </bndbox>
    </object>
    <object>
        <name>37352</name>
        <difficult>0</difficult>
        <bndbox>
            <xmin>387</xmin>
            <ymin>419</ymin>
            <xmax>531</xmax>
            <ymax>540</ymax>
        </bndbox>
    </object>
    <object>
        <name>2780</name>
        <difficult>0</difficult>
        <bndbox>
            <xmin>0</xmin>
            <ymin>337</ymin>
            <xmax>113</xmax>
            <ymax>420</ymax>
        </bndbox>
    </object>
</annotation>
