<?xml version="1.0" ?>
<annotation>
    <folder>BrickRay</folder>
    <filename>98306112-db7f-11eb-92fb-3497f683a169.jpg</filename>
    <size>
        <width>600</width>
        <height>600</height>
        <depth>3</depth>
    </size>
    <object>
        <name>3036</name>
        <difficult>0</difficult>
        <bndbox>
            <xmin>253</xmin>
            <ymin>112</ymin>
            <xmax>600</xmax>
            <ymax>425</ymax>
        </bndbox>
    </object>
    <object>
        <name>4162</name>
        <difficult>0</difficult>
        <bndbox>
            <xmin>0</xmin>
            <ymin>222</ymin>
            <xmax>254</xmax>
            <ymax>430</ymax>
        </bndbox>
    </object>
    <object>
        <name>6231</name>
        <difficult>0</difficult>
        <bndbox>
            <xmin>400</xmin>
            <ymin>151</ymin>
            <xmax>454</xmax>
            <ymax>213</ymax>
        </bndbox>
    </object>
    <object>
        <name>90540</name>
        <difficult>0</difficult>
        <bndbox>
            <xmin>357</xmin>
            <ymin>419</ymin>
            <xmax>388</xmax>
            <ymax>464</ymax>
        </bndbox>
    </object>
</annotation>
