<?xml version="1.0" ?>
<annotation>
    <folder>BrickRay</folder>
    <filename>9a73b088-daf9-11eb-bb99-3497f683a169.jpg</filename>
    <size>
        <width>600</width>
        <height>600</height>
        <depth>3</depth>
    </size>
    <object>
        <name>54383</name>
        <difficult>0</difficult>
        <bndbox>
            <xmin>169</xmin>
            <ymin>310</ymin>
            <xmax>445</xmax>
            <ymax>600</ymax>
        </bndbox>
    </object>
    <object>
        <name>15392</name>
        <difficult>0</difficult>
        <bndbox>
            <xmin>454</xmin>
            <ymin>0</ymin>
            <xmax>493</xmax>
            <ymax>38</ymax>
        </bndbox>
    </object>
    <object>
        <name>6231</name>
        <difficult>0</difficult>
        <bndbox>
            <xmin>434</xmin>
            <ymin>62</ymin>
            <xmax>491</xmax>
            <ymax>128</ymax>
        </bndbox>
    </object>
    <object>
        <name>3633</name>
        <difficult>0</difficult>
        <bndbox>
            <xmin>156</xmin>
            <ymin>14</ymin>
            <xmax>267</xmax>
            <ymax>112</ymax>
        </bndbox>
    </object>
</annotation>
