<?xml version="1.0" ?>
<annotation>
    <folder>BrickRay</folder>
    <filename>9d3076b4-e665-11eb-8f36-b0c090bd3910.jpg</filename>
    <size>
        <width>300</width>
        <height>300</height>
        <depth>3</depth>
    </size>
    <object>
        <name>39739</name>
        <difficult>0</difficult>
        <bndbox>
            <xmin>0</xmin>
            <ymin>22</ymin>
            <xmax>50</xmax>
            <ymax>65</ymax>
        </bndbox>
    </object>
    <object>
        <name>15395</name>
        <difficult>0</difficult>
        <bndbox>
            <xmin>196</xmin>
            <ymin>169</ymin>
            <xmax>299</xmax>
            <ymax>269</ymax>
        </bndbox>
    </object>
</annotation>
