<?xml version="1.0" ?>
<annotation>
    <folder>BrickRay</folder>
    <filename>9d3f4370-da65-11eb-8217-3497f683a169.jpg</filename>
    <size>
        <width>600</width>
        <height>600</height>
        <depth>3</depth>
    </size>
    <object>
        <name>60596</name>
        <difficult>0</difficult>
        <bndbox>
            <xmin>339</xmin>
            <ymin>189</ymin>
            <xmax>599</xmax>
            <ymax>475</ymax>
        </bndbox>
    </object>
    <object>
        <name>30350b</name>
        <difficult>0</difficult>
        <bndbox>
            <xmin>0</xmin>
            <ymin>100</ymin>
            <xmax>143</xmax>
            <ymax>226</ymax>
        </bndbox>
    </object>
    <object>
        <name>2432</name>
        <difficult>0</difficult>
        <bndbox>
            <xmin>416</xmin>
            <ymin>9</ymin>
            <xmax>492</xmax>
            <ymax>85</ymax>
        </bndbox>
    </object>
    <object>
        <name>2654</name>
        <difficult>0</difficult>
        <bndbox>
            <xmin>166</xmin>
            <ymin>492</ymin>
            <xmax>258</xmax>
            <ymax>587</ymax>
        </bndbox>
    </object>
</annotation>
