<?xml version="1.0" ?>
<annotation>
    <folder>BrickRay</folder>
    <filename>9ef1dc50-da47-11eb-9ed7-3497f683a169.jpg</filename>
    <size>
        <width>600</width>
        <height>600</height>
        <depth>3</depth>
    </size>
    <object>
        <name>3029</name>
        <difficult>0</difficult>
        <bndbox>
            <xmin>373</xmin>
            <ymin>162</ymin>
            <xmax>599</xmax>
            <ymax>506</ymax>
        </bndbox>
    </object>
    <object>
        <name>2458</name>
        <difficult>0</difficult>
        <bndbox>
            <xmin>0</xmin>
            <ymin>250</ymin>
            <xmax>71</xmax>
            <ymax>324</ymax>
        </bndbox>
    </object>
    <object>
        <name>3938</name>
        <difficult>0</difficult>
        <bndbox>
            <xmin>305</xmin>
            <ymin>71</ymin>
            <xmax>342</xmax>
            <ymax>124</ymax>
        </bndbox>
    </object>
    <object>
        <name>32474</name>
        <difficult>0</difficult>
        <bndbox>
            <xmin>87</xmin>
            <ymin>334</ymin>
            <xmax>128</xmax>
            <ymax>374</ymax>
        </bndbox>
    </object>
</annotation>
