<?xml version="1.0" ?>
<annotation>
    <folder>BrickRay</folder>
    <filename>aa42850a-e2e8-11eb-9d5d-b0c090bd3910.jpg</filename>
    <size>
        <width>600</width>
        <height>600</height>
        <depth>3</depth>
    </size>
    <object>
        <name>3942c</name>
        <difficult>0</difficult>
        <bndbox>
            <xmin>75</xmin>
            <ymin>94</ymin>
            <xmax>165</xmax>
            <ymax>229</ymax>
        </bndbox>
    </object>
    <object>
        <name>42003</name>
        <difficult>0</difficult>
        <bndbox>
            <xmin>161</xmin>
            <ymin>0</ymin>
            <xmax>225</xmax>
            <ymax>125</ymax>
        </bndbox>
    </object>
    <object>
        <name>3297</name>
        <difficult>0</difficult>
        <bndbox>
            <xmin>207</xmin>
            <ymin>336</ymin>
            <xmax>503</xmax>
            <ymax>599</ymax>
        </bndbox>
    </object>
    <object>
        <name>22885</name>
        <difficult>0</difficult>
        <bndbox>
            <xmin>219</xmin>
            <ymin>316</ymin>
            <xmax>352</xmax>
            <ymax>493</ymax>
        </bndbox>
    </object>
</annotation>
