<?xml version="1.0" ?>
<annotation>
    <folder>BrickRay</folder>
    <filename>b0b7b476-d9c7-11eb-9ca5-3497f683a169.jpg</filename>
    <size>
        <width>600</width>
        <height>600</height>
        <depth>3</depth>
    </size>
    <object>
        <name>6126b</name>
        <difficult>0</difficult>
        <bndbox>
            <xmin>144</xmin>
            <ymin>266</ymin>
            <xmax>264</xmax>
            <ymax>320</ymax>
        </bndbox>
    </object>
    <object>
        <name>62462</name>
        <difficult>0</difficult>
        <bndbox>
            <xmin>399</xmin>
            <ymin>249</ymin>
            <xmax>454</xmax>
            <ymax>321</ymax>
        </bndbox>
    </object>
    <object>
        <name>26047</name>
        <difficult>0</difficult>
        <bndbox>
            <xmin>286</xmin>
            <ymin>541</ymin>
            <xmax>359</xmax>
            <ymax>600</ymax>
        </bndbox>
    </object>
    <object>
        <name>99773</name>
        <difficult>0</difficult>
        <bndbox>
            <xmin>242</xmin>
            <ymin>0</ymin>
            <xmax>344</xmax>
            <ymax>113</ymax>
        </bndbox>
    </object>
</annotation>
