<?xml version="1.0" ?>
<annotation>
    <folder>BrickRay</folder>
    <filename>b68dc854-e69b-11eb-b500-b0c090bd3910.jpg</filename>
    <size>
        <width>300</width>
        <height>300</height>
        <depth>3</depth>
    </size>
    <object>
        <name>95344</name>
        <difficult>0</difficult>
        <bndbox>
            <xmin>177</xmin>
            <ymin>256</ymin>
            <xmax>195</xmax>
            <ymax>299</ymax>
        </bndbox>
    </object>
    <object>
        <name>91988</name>
        <difficult>0</difficult>
        <bndbox>
            <xmin>102</xmin>
            <ymin>0</ymin>
            <xmax>210</xmax>
            <ymax>280</ymax>
        </bndbox>
    </object>
</annotation>
