<?xml version="1.0" ?>
<annotation>
    <folder>BrickRay</folder>
    <filename>b87db1d4-e4ac-11eb-9336-b0c090bd3910.jpg</filename>
    <size>
        <width>600</width>
        <height>600</height>
        <depth>3</depth>
    </size>
    <object>
        <name>4490</name>
        <difficult>0</difficult>
        <bndbox>
            <xmin>459</xmin>
            <ymin>0</ymin>
            <xmax>566</xmax>
            <ymax>130</ymax>
        </bndbox>
    </object>
    <object>
        <name>41769</name>
        <difficult>0</difficult>
        <bndbox>
            <xmin>140</xmin>
            <ymin>409</ymin>
            <xmax>412</xmax>
            <ymax>600</ymax>
        </bndbox>
    </object>
    <object>
        <name>26047</name>
        <difficult>0</difficult>
        <bndbox>
            <xmin>49</xmin>
            <ymin>472</ymin>
            <xmax>168</xmax>
            <ymax>581</ymax>
        </bndbox>
    </object>
    <object>
        <name>87747</name>
        <difficult>0</difficult>
        <bndbox>
            <xmin>197</xmin>
            <ymin>248</ymin>
            <xmax>262</xmax>
            <ymax>321</ymax>
        </bndbox>
    </object>
</annotation>
