<?xml version="1.0" ?>
<annotation>
    <folder>BrickRay</folder>
    <filename>bb12f43a-db43-11eb-b814-3497f683a169.jpg</filename>
    <size>
        <width>600</width>
        <height>600</height>
        <depth>3</depth>
    </size>
    <object>
        <name>17485</name>
        <difficult>0</difficult>
        <bndbox>
            <xmin>290</xmin>
            <ymin>409</ymin>
            <xmax>435</xmax>
            <ymax>562</ymax>
        </bndbox>
    </object>
    <object>
        <name>24375</name>
        <difficult>0</difficult>
        <bndbox>
            <xmin>550</xmin>
            <ymin>0</ymin>
            <xmax>599</xmax>
            <ymax>48</ymax>
        </bndbox>
    </object>
    <object>
        <name>6231</name>
        <difficult>0</difficult>
        <bndbox>
            <xmin>259</xmin>
            <ymin>490</ymin>
            <xmax>362</xmax>
            <ymax>600</ymax>
        </bndbox>
    </object>
    <object>
        <name>23950</name>
        <difficult>0</difficult>
        <bndbox>
            <xmin>0</xmin>
            <ymin>242</ymin>
            <xmax>171</xmax>
            <ymax>435</ymax>
        </bndbox>
    </object>
</annotation>
