<?xml version="1.0" ?>
<annotation>
    <folder>BrickRay</folder>
    <filename>bc125fe8-e668-11eb-86b9-b0c090bd3910.jpg</filename>
    <size>
        <width>300</width>
        <height>300</height>
        <depth>3</depth>
    </size>
    <object>
        <name>40345</name>
        <difficult>0</difficult>
        <bndbox>
            <xmin>0</xmin>
            <ymin>3</ymin>
            <xmax>299</xmax>
            <ymax>251</ymax>
        </bndbox>
    </object>
    <object>
        <name>87580</name>
        <difficult>0</difficult>
        <bndbox>
            <xmin>172</xmin>
            <ymin>208</ymin>
            <xmax>260</xmax>
            <ymax>296</ymax>
        </bndbox>
    </object>
</annotation>
