<?xml version="1.0" ?>
<annotation>
    <folder>BrickRay</folder>
    <filename>c04e8c18-e2ff-11eb-8ca2-b0c090bd3910.jpg</filename>
    <size>
        <width>600</width>
        <height>600</height>
        <depth>3</depth>
    </size>
    <object>
        <name>35464</name>
        <difficult>0</difficult>
        <bndbox>
            <xmin>352</xmin>
            <ymin>0</ymin>
            <xmax>405</xmax>
            <ymax>45</ymax>
        </bndbox>
    </object>
    <object>
        <name>2780</name>
        <difficult>0</difficult>
        <bndbox>
            <xmin>181</xmin>
            <ymin>259</ymin>
            <xmax>311</xmax>
            <ymax>322</ymax>
        </bndbox>
    </object>
    <object>
        <name>30176</name>
        <difficult>0</difficult>
        <bndbox>
            <xmin>278</xmin>
            <ymin>343</ymin>
            <xmax>497</xmax>
            <ymax>600</ymax>
        </bndbox>
    </object>
    <object>
        <name>4032</name>
        <difficult>0</difficult>
        <bndbox>
            <xmin>71</xmin>
            <ymin>219</ymin>
            <xmax>195</xmax>
            <ymax>325</ymax>
        </bndbox>
    </object>
</annotation>
