<?xml version="1.0" ?>
<annotation>
    <folder>BrickRay</folder>
    <filename>d26bcea8-dad4-11eb-80a6-3497f683a169.jpg</filename>
    <size>
        <width>600</width>
        <height>600</height>
        <depth>3</depth>
    </size>
    <object>
        <name>30162</name>
        <difficult>0</difficult>
        <bndbox>
            <xmin>182</xmin>
            <ymin>110</ymin>
            <xmax>269</xmax>
            <ymax>171</ymax>
        </bndbox>
    </object>
    <object>
        <name>11209</name>
        <difficult>0</difficult>
        <bndbox>
            <xmin>119</xmin>
            <ymin>1</ymin>
            <xmax>217</xmax>
            <ymax>173</ymax>
        </bndbox>
    </object>
    <object>
        <name>2412b</name>
        <difficult>0</difficult>
        <bndbox>
            <xmin>331</xmin>
            <ymin>423</ymin>
            <xmax>441</xmax>
            <ymax>599</ymax>
        </bndbox>
    </object>
    <object>
        <name>6558</name>
        <difficult>0</difficult>
        <bndbox>
            <xmin>182</xmin>
            <ymin>0</ymin>
            <xmax>225</xmax>
            <ymax>126</ymax>
        </bndbox>
    </object>
</annotation>
