<?xml version="1.0" ?>
<annotation>
    <folder>BrickRay</folder>
    <filename>d4cfd6b6-d93f-11eb-b0af-b0c090bd3910.jpg</filename>
    <size>
        <width>600</width>
        <height>600</height>
        <depth>3</depth>
    </size>
    <object>
        <name>18977</name>
        <difficult>0</difficult>
        <bndbox>
            <xmin>450</xmin>
            <ymin>328</ymin>
            <xmax>599</xmax>
            <ymax>483</ymax>
        </bndbox>
    </object>
    <object>
        <name>47397</name>
        <difficult>0</difficult>
        <bndbox>
            <xmin>5</xmin>
            <ymin>77</ymin>
            <xmax>319</xmax>
            <ymax>402</ymax>
        </bndbox>
    </object>
    <object>
        <name>3678b</name>
        <difficult>0</difficult>
        <bndbox>
            <xmin>321</xmin>
            <ymin>143</ymin>
            <xmax>432</xmax>
            <ymax>294</ymax>
        </bndbox>
    </object>
    <object>
        <name>3737</name>
        <difficult>0</difficult>
        <bndbox>
            <xmin>0</xmin>
            <ymin>214</ymin>
            <xmax>354</xmax>
            <ymax>478</ymax>
        </bndbox>
    </object>
</annotation>
