<?xml version="1.0" ?>
<annotation>
    <folder>BrickRay</folder>
    <filename>e020e31e-e7c1-11eb-b65a-b0c090bd3910.jpg</filename>
    <size>
        <width>300</width>
        <height>300</height>
        <depth>3</depth>
    </size>
    <object>
        <name>3700</name>
        <difficult>0</difficult>
        <bndbox>
            <xmin>128</xmin>
            <ymin>93</ymin>
            <xmax>261</xmax>
            <ymax>300</ymax>
        </bndbox>
    </object>
    <object>
        <name>6553</name>
        <difficult>0</difficult>
        <bndbox>
            <xmin>53</xmin>
            <ymin>0</ymin>
            <xmax>152</xmax>
            <ymax>224</ymax>
        </bndbox>
    </object>
</annotation>
