<?xml version="1.0" ?>
<annotation>
    <folder>BrickRay</folder>
    <filename>e4f7b412-da64-11eb-a092-3497f683a169.jpg</filename>
    <size>
        <width>600</width>
        <height>600</height>
        <depth>3</depth>
    </size>
    <object>
        <name>87083</name>
        <difficult>0</difficult>
        <bndbox>
            <xmin>64</xmin>
            <ymin>130</ymin>
            <xmax>211</xmax>
            <ymax>205</ymax>
        </bndbox>
    </object>
    <object>
        <name>3831</name>
        <difficult>0</difficult>
        <bndbox>
            <xmin>77</xmin>
            <ymin>352</ymin>
            <xmax>189</xmax>
            <ymax>464</ymax>
        </bndbox>
    </object>
    <object>
        <name>6126b</name>
        <difficult>0</difficult>
        <bndbox>
            <xmin>546</xmin>
            <ymin>108</ymin>
            <xmax>600</xmax>
            <ymax>218</ymax>
        </bndbox>
    </object>
    <object>
        <name>3245c</name>
        <difficult>0</difficult>
        <bndbox>
            <xmin>0</xmin>
            <ymin>167</ymin>
            <xmax>121</xmax>
            <ymax>285</ymax>
        </bndbox>
    </object>
</annotation>
