<?xml version="1.0" ?>
<annotation>
    <folder>BrickRay</folder>
    <filename>e80b9d5c-d94a-11eb-b1c0-b0c090bd3910.jpg</filename>
    <size>
        <width>600</width>
        <height>600</height>
        <depth>3</depth>
    </size>
    <object>
        <name>60608</name>
        <difficult>0</difficult>
        <bndbox>
            <xmin>264</xmin>
            <ymin>480</ymin>
            <xmax>342</xmax>
            <ymax>563</ymax>
        </bndbox>
    </object>
    <object>
        <name>33909</name>
        <difficult>0</difficult>
        <bndbox>
            <xmin>282</xmin>
            <ymin>248</ymin>
            <xmax>362</xmax>
            <ymax>318</ymax>
        </bndbox>
    </object>
    <object>
        <name>3006</name>
        <difficult>0</difficult>
        <bndbox>
            <xmin>250</xmin>
            <ymin>0</ymin>
            <xmax>384</xmax>
            <ymax>193</ymax>
        </bndbox>
    </object>
    <object>
        <name>53585</name>
        <difficult>0</difficult>
        <bndbox>
            <xmin>235</xmin>
            <ymin>544</ymin>
            <xmax>288</xmax>
            <ymax>600</ymax>
        </bndbox>
    </object>
</annotation>
