<?xml version="1.0" ?>
<annotation>
    <folder>BrickRay</folder>
    <filename>eba5d734-daf0-11eb-adec-3497f683a169.jpg</filename>
    <size>
        <width>600</width>
        <height>600</height>
        <depth>3</depth>
    </size>
    <object>
        <name>15391</name>
        <difficult>0</difficult>
        <bndbox>
            <xmin>129</xmin>
            <ymin>118</ymin>
            <xmax>208</xmax>
            <ymax>169</ymax>
        </bndbox>
    </object>
    <object>
        <name>16577</name>
        <difficult>0</difficult>
        <bndbox>
            <xmin>140</xmin>
            <ymin>0</ymin>
            <xmax>295</xmax>
            <ymax>275</ymax>
        </bndbox>
    </object>
    <object>
        <name>3960</name>
        <difficult>0</difficult>
        <bndbox>
            <xmin>159</xmin>
            <ymin>8</ymin>
            <xmax>287</xmax>
            <ymax>117</ymax>
        </bndbox>
    </object>
    <object>
        <name>3065</name>
        <difficult>0</difficult>
        <bndbox>
            <xmin>371</xmin>
            <ymin>494</ymin>
            <xmax>446</xmax>
            <ymax>600</ymax>
        </bndbox>
    </object>
</annotation>
