<?xml version="1.0" ?>
<annotation>
    <folder>BrickRay</folder>
    <filename>f2cb9d18-db37-11eb-99f8-3497f683a169.jpg</filename>
    <size>
        <width>600</width>
        <height>600</height>
        <depth>3</depth>
    </size>
    <object>
        <name>14769</name>
        <difficult>0</difficult>
        <bndbox>
            <xmin>0</xmin>
            <ymin>424</ymin>
            <xmax>89</xmax>
            <ymax>510</ymax>
        </bndbox>
    </object>
    <object>
        <name>6259</name>
        <difficult>0</difficult>
        <bndbox>
            <xmin>83</xmin>
            <ymin>2</ymin>
            <xmax>253</xmax>
            <ymax>220</ymax>
        </bndbox>
    </object>
    <object>
        <name>93274</name>
        <difficult>0</difficult>
        <bndbox>
            <xmin>103</xmin>
            <ymin>172</ymin>
            <xmax>246</xmax>
            <ymax>289</ymax>
        </bndbox>
    </object>
    <object>
        <name>16577</name>
        <difficult>0</difficult>
        <bndbox>
            <xmin>278</xmin>
            <ymin>329</ymin>
            <xmax>600</xmax>
            <ymax>597</ymax>
        </bndbox>
    </object>
</annotation>
