<?xml version="1.0" ?>
<annotation>
    <folder>BrickRay</folder>
    <filename>fe1f5d9c-e78d-11eb-828d-b0c090bd3910.jpg</filename>
    <size>
        <width>300</width>
        <height>300</height>
        <depth>3</depth>
    </size>
    <object>
        <name>4865</name>
        <difficult>0</difficult>
        <bndbox>
            <xmin>128</xmin>
            <ymin>168</ymin>
            <xmax>209</xmax>
            <ymax>300</ymax>
        </bndbox>
    </object>
    <object>
        <name>30044</name>
        <difficult>0</difficult>
        <bndbox>
            <xmin>95</xmin>
            <ymin>0</ymin>
            <xmax>189</xmax>
            <ymax>185</ymax>
        </bndbox>
    </object>
</annotation>
