<?xml version="1.0" ?>
<annotation>
    <folder>BrickRay</folder>
    <filename>ff1a86e8-e65e-11eb-b3cf-b0c090bd3910.jpg</filename>
    <size>
        <width>300</width>
        <height>300</height>
        <depth>3</depth>
    </size>
    <object>
        <name>52107</name>
        <difficult>0</difficult>
        <bndbox>
            <xmin>222</xmin>
            <ymin>151</ymin>
            <xmax>299</xmax>
            <ymax>218</ymax>
        </bndbox>
    </object>
    <object>
        <name>32525</name>
        <difficult>0</difficult>
        <bndbox>
            <xmin>0</xmin>
            <ymin>14</ymin>
            <xmax>184</xmax>
            <ymax>282</ymax>
        </bndbox>
    </object>
</annotation>
